rbql/__init__.py
rbql/__main__.py
rbql/_version.py
rbql/csv_utils.py
rbql/rbql_csv.py
rbql/rbql_engine.py
rbql/rbql_ipython.py
rbql/rbql_main.py
rbql/rbql_pandas.py
rbql/rbql_sqlite.py
rbql-0.29.0.dist-info/LICENSE
rbql-0.29.0.dist-info/METADATA
rbql-0.29.0.dist-info/WHEEL
rbql-0.29.0.dist-info/entry_points.txt
rbql-0.29.0.dist-info/top_level.txt
rbql-0.29.0.dist-info/RECORD
