Metadata-Version: 2.1
Name: rbql
Version: 0.29.0
Summary: Rainbow Query Language
Home-page: https://github.com/mechatroner/RBQL
Author: Dmitry Ignatovich
Author-email: mechatroner@yandex.ru
License: UNKNOWN
Keywords: SQL SQL-like transpiler RBQL library CLI command-line CSV TSV IPython Jupyter
Platform: UNKNOWN
Classifier: Programming Language :: Python
Classifier: Programming Language :: Python :: 3
Classifier: License :: OSI Approved :: MIT License
Classifier: Operating System :: OS Independent
Classifier: Framework :: IPython
License-File: LICENSE
